trigger_model/__init__.py
trigger_model/core.py
trigger_model/mlflow_wrapper.py
trigger_model/templates/__init__.py
trigger_model-0.1.3.dist-info/METADATA
trigger_model-0.1.3.dist-info/WHEEL
trigger_model-0.1.3.dist-info/top_level.txt
trigger_model-0.1.3.dist-info/RECORD
